README.md
setup.py
percolation/__init__.py
percolation/bootstrap.py
percolation.egg-info/PKG-INFO
percolation.egg-info/SOURCES.txt
percolation.egg-info/dependency_links.txt
percolation.egg-info/requires.txt
percolation.egg-info/top_level.txt
percolation/analysis/__init__.py
percolation/analysis/pca.py
percolation/analysis/sectorialize.py
percolation/legacy/__init__.py
percolation/legacy/analyses/__init__.py
percolation/legacy/analyses/textual.py
percolation/legacy/analyses/topological.py
percolation/legacy/outlines/__init__.py
percolation/legacy/outlines/articleStability.py
percolation/legacy/outlines/articles.py
percolation/legacy/outlines/demo.py
percolation/legacy/triples/__init__.py
percolation/legacy/triples/datasets.py
percolation/legacy/triples/notes.py
percolation/measures/__init__.py
percolation/measures/authors/__init__.py
percolation/measures/authors/authorsStatistics.py
percolation/measures/evolution/__init__.py
percolation/measures/evolution/networkEvolution.py
percolation/measures/text/__init__.py
percolation/measures/text/aux.py
percolation/measures/text/overall.py
percolation/measures/text/pos.py
percolation/measures/text/raw.py
percolation/measures/text/tfIdf.py
percolation/measures/text/wordnet.py
percolation/measures/topology/__init__.py
percolation/measures/topology/directMeasures.py
percolation/measures/topology/erdosSectors.py
percolation/measures/topology/powerLawFit.py
percolation/mediaRendering/__init__.py
percolation/mediaRendering/figures.py
percolation/mediaRendering/tables.py
percolation/rdf/__init__.py
percolation/rdf/inference.py
percolation/rdf/ontology.py
percolation/rdf/probeOntology.py
percolation/rdf/publishing.py
percolation/rdf/rdflib.py
percolation/rdf/sparql/__init__.py
percolation/rdf/sparql/classes.py
percolation/rdf/sparql/configFuseki.py
percolation/rdf/sparql/functions.py
percolation/rdf/sparql/sparqlOLD.py
percolation/rdf/sparql/tests.py
percolation/utils/__init__.py
percolation/utils/general.py
percolation/utils/status.py